pyvboxcli.py
pyvboxcli-0.2.1.dist-info/entry_points.txt
pyvboxcli-0.2.1.dist-info/WHEEL
pyvboxcli-0.2.1.dist-info/METADATA
pyvboxcli-0.2.1.dist-info/RECORD
