Metadata-Version: 2.1
Name: pyvboxcli
Version: 0.2.1
Summary: PYthon wrapper for VirtualBOX Command-Line Interface
Requires-Dist: waiting
Requires-Dist: black ; extra == "dev"
Requires-Dist: isort ; extra == "dev"
Requires-Dist: mypy ; extra == "dev"
Requires-Dist: pre-commit ; extra == "dev"
Requires-Dist: sphinx ; extra == "docs"
Requires-Dist: sphinx-argparse ; extra == "docs"
Requires-Dist: sphinx-rtd-theme ; extra == "docs"
Requires-Dist: pexpect ; extra == "test"
Requires-Dist: pytest ; extra == "test"
Requires-Dist: pytest-cov ; extra == "test"
Requires-Dist: tox ; extra == "test"
Requires-Dist: python-vagrant ; extra == "test"
Project-URL: Documentation, https://cdleonard.gitlab.io/pyvboxcli/sphinx/
Project-URL: Homepage, https://gitlab.com/cdleonard/pyvboxcli
Provides-Extra: dev
Provides-Extra: docs
Provides-Extra: test
